Workbook

Sheet Dashboard
A1: LOAN DASHBOARD

Sheet New
A3: Loan Amount | B3: 79012500 | D3: Monthly | E3: 12 | G3: Monthly | H3: 1
A4: Interest Rate | B4: 0.29 | D4: Quarterly | E4: 4 | G4: Quarterly | H4: 3
A5: Loan Term (Years) | B5: 3 | D5: Annual | E5: 1 | G5: Annual | H5: 12
A6: Start Date | B6: 46023
A7: Payment Frequency | B7: Monthly
A8: Payment Period | B8: =VLOOKUP(B7,D3:E5,2,FALSE) -> 12
A9: Payment Date Period | B9: =VLOOKUP(B7,G3:H5,2,FALSE) -> 1
A13: Metric
A14: Original Loan | B14: =B3 -> 79012500
A15: Total Payments | B15: =Old!D44 -> 1.1919871e+08
A16: Total Interest Paid | B16: =Old!E44 -> 40186213
A17: Total Principal Paid | B17: =Old!F44 -> 79012500
A18: Total extra Principal | B18: =Old!G44 -> 0
A19: Ending Balance | B19: =Old!H42 -> 0
A20: Loan Progress % | B20: =(B14-B19)/B14 -> 1

Sheet Old
A1: Principal: | B1: =New!B3 -> 79012500 | C1: Number of Payment: | D1: =New!B5*New!B8 -> 36
A2: Terms: | B2: =New!B5 -> 3 | C2: Rate Per Period: | D2: =B3/New!B8 -> 0.024166667
A3: Annual Rate: | B3: =New!B4 -> 0.29 | C3: Payment: | D3: =PMT(D2,D1,-B1,0) -> 3311075.4
A4: Initial Date: | B4: =New!B6 -> 46023
A6: Months | B6: Date | C6: Beginning Bal | D6: Payment | E6: Interest | F6: Principal | G6: Extra Principal Payment | H6: Ending Balance
A7: Month 1 | B7: =New!B6 -> 46023 | C7: =B1 -> 79012500 | D7: =IF(C7=0,0,$D$3) -> 3311075.4 | E7: =IF(C7=0,0,C7*$D$2) -> 1909468.8 | F7: =IF(C7=0,0,D7-E7) -> 1401606.6 | H7: =MAX(0,C7-F7-G7) -> 77610893
A8: Month 2 | B8: =EDATE(B7,New!$B$9) -> 46054 | C8: =H7 -> 77610893 | D8: =IF(C8=0,0,$D$3) -> 3311075.4 | E8: =IF(C8=0,0,C8*$D$2) -> 1875596.6 | F8: =IF(C8=0,0,D8-E8) -> 1435478.8 | H8: =MAX(0,C8-F8-G8) -> 76175415
A9: Month 3 | B9: =EDATE(B8,New!$B$9) -> 46082 | C9: =H8 -> 76175415 | D9: =IF(C9=0,0,$D$3) -> 3311075.4 | E9: =IF(C9=0,0,C9*$D$2) -> 1840905.9 | F9: =IF(C9=0,0,D9-E9) -> 1470169.5 | H9: =MAX(0,C9-F9-G9) -> 74705245
A10: Month 4 | B10: =EDATE(B9,New!$B$9) -> 46113 | C10: =H9 -> 74705245 | D10: =IF(C10=0,0,$D$3) -> 3311075.4 | E10: =IF(C10=0,0,C10*$D$2) -> 1805376.8 | F10: =IF(C10=0,0,D10-E10) -> 1505698.6 | H10: =MAX(0,C10-F10-G10) -> 73199546
A11: Month 5 | B11: =EDATE(B10,New!$B$9) -> 46143 | C11: =H10 -> 73199546 | D11: =IF(C11=0,0,$D$3) -> 3311075.4 | E11: =IF(C11=0,0,C11*$D$2) -> 1768989 | F11: =IF(C11=0,0,D11-E11) -> 1542086.3 | H11: =MAX(0,C11-F11-G11) -> 71657460
A12: Month 6 | B12: =EDATE(B11,New!$B$9) -> 46174 | C12: =H11 -> 71657460 | D12: =IF(C12=0,0,$D$3) -> 3311075.4 | E12: =IF(C12=0,0,C12*$D$2) -> 1731722 | F12: =IF(C12=0,0,D12-E12) -> 1579353.4 | H12: =MAX(0,C12-F12-G12) -> 70078107
A13: Month 7 | B13: =EDATE(B12,New!$B$9) -> 46204 | C13: =H12 -> 70078107 | D13: =IF(C13=0,0,$D$3) -> 3311075.4 | E13: =IF(C13=0,0,C13*$D$2) -> 1693554.2 | F13: =IF(C13=0,0,D13-E13) -> 1617521.1 | H13: =MAX(0,C13-F13-G13) -> 68460586
A14: Month 8 | B14: =EDATE(B13,New!$B$9) -> 46235 | C14: =H13 -> 68460586 | D14: =IF(C14=0,0,$D$3) -> 3311075.4 | E14: =IF(C14=0,0,C14*$D$2) -> 1654464.2 | F14: =IF(C14=0,0,D14-E14) -> 1656611.2 | H14: =MAX(0,C14-F14-G14) -> 66803974
A15: Month 9 | B15: =EDATE(B14,New!$B$9) -> 46266 | C15: =H14 -> 66803974 | D15: =IF(C15=0,0,$D$3) -> 3311075.4 | E15: =IF(C15=0,0,C15*$D$2) -> 1614429.4 | F15: =IF(C15=0,0,D15-E15) -> 1696646 | H15: =MAX(0,C15-F15-G15) -> 65107328
A16: Month 10 | B16: =EDATE(B15,New!$B$9) -> 46296 | C16: =H15 -> 65107328 | D16: =IF(C16=0,0,$D$3) -> 3311075.4 | E16: =IF(C16=0,0,C16*$D$2) -> 1573427.1 | F16: =IF(C16=0,0,D16-E16) -> 1737648.3 | H16: =MAX(0,C16-F16-G16) -> 63369680
A17: Month 11 | B17: =EDATE(B16,New!$B$9) -> 46327 | C17: =H16 -> 63369680 | D17: =IF(C17=0,0,$D$3) -> 3311075.4 | E17: =IF(C17=0,0,C17*$D$2) -> 1531433.9 | F17: =IF(C17=0,0,D17-E17) -> 1779641.4 | H17: =MAX(0,C17-F17-G17) -> 61590039
A18: Month 12 | B18: =EDATE(B17,New!$B$9) -> 46357 | C18: =H17 -> 61590039 | D18: =IF(C18=0,0,$D$3) -> 3311075.4 | E18: =IF(C18=0,0,C18*$D$2) -> 1488425.9 | F18: =IF(C18=0,0,D18-E18) -> 1822649.4 | H18: =MAX(0,C18-F18-G18) -> 59767389
A19: Month 13 | B19: =EDATE(B18,New!$B$9) -> 46388 | C19: =H18 -> 59767389 | D19: =IF(C19=0,0,$D$3) -> 3311075.4 | E19: =IF(C19=0,0,C19*$D$2) -> 1444378.6 | F19: =IF(C19=0,0,D19-E19) -> 1866696.8 | H19: =MAX(0,C19-F19-G19) -> 57900692
... A42: Month 36 | B42: =EDATE(B41,New!$B$9) -> 47088 | C42: =H41 -> 3232945.8 | D42: =IF(C42=0,0,$D$3) -> 3311075.4 | E42: =IF(C42=0,0,C42*$D$2) -> 78129.525 | F42: =IF(C42=0,0,D42-E42) -> 3232945.8 | H42: =MAX(0,C42-F42-G42) -> 0
D44: =SUM(D7:D43) -> 1.1919871e+08 | E44: =SUM(E7:E43) -> 40186213 | F44: =SUM(F7:F43) -> 79012500 | G44: =SUM(G7:G43) -> 0
